pujbapy/__init__.py
pujbapy/intervalos.py
pujbapy/modelos.py
pujbapy/pruebas.py
pujbapy/utils.py
pujbapy/visualizacion.py
pujbapy-0.0.9.dist-info/LICENSE
pujbapy-0.0.9.dist-info/METADATA
pujbapy-0.0.9.dist-info/WHEEL
pujbapy-0.0.9.dist-info/top_level.txt
pujbapy-0.0.9.dist-info/RECORD
