Metadata-Version: 2.1
Name: pujbapy
Version: 0.0.9
Summary: Package for BA class
Author-email: Carlos Ortiz <carlosortizbon@gmail.com>
Project-URL: Homepage, https://github.com/cortizbon/pujbapy
Project-URL: Issues, https://github.com/cortizbon/pujbapy/issues
Classifier: Programming Language :: Python :: 3
Classifier: License :: OSI Approved :: MIT License
Classifier: Operating System :: OS Independent
Requires-Python: >=3.8
License-File: LICENSE
